codeUtils/__init__.py
codeUtils/decorator/__init__.py
codeUtils/decorator/error_decorator.py
codeUtils/decorator/exec_time.py
codeUtils/decorator/registry.py
codeUtils/display/__init__.py
codeUtils/display/histogram.py
codeUtils/log_tools/__init__.py
codeUtils/log_tools/log_config.py
codeUtils/match_factory/__init__.py
codeUtils/match_factory/bbox_match.py
codeUtils/match_factory/shape_match.py
codeUtils/matrix/__init__.py
codeUtils/matrix/confusion_matrix.py
codeUtils/scheduler/__init__.py
codeUtils/scheduler/base_operator.py
codeUtils/scheduler/param_object.py
codeUtils/scheduler/task_manage.py
codeUtils/tools/__init__.py
codeUtils/tools/cache_file.py
codeUtils/tools/font_config.py
codeUtils/tools/obj_trans.py
codeUtils_elfin-0.1.4.dist-info/LICENSE
codeUtils_elfin-0.1.4.dist-info/METADATA
codeUtils_elfin-0.1.4.dist-info/WHEEL
codeUtils_elfin-0.1.4.dist-info/top_level.txt
codeUtils_elfin-0.1.4.dist-info/RECORD
